noos_inv/__init__.py
noos_inv/__main__.py
noos_inv/collections.py
noos_inv/exceptions.py
noos_inv/tasks/__init__.py
noos_inv/tasks/docker.py
noos_inv/tasks/git.py
noos_inv/tasks/helm.py
noos_inv/tasks/local.py
noos_inv/tasks/python.py
noos_inv/tasks/terraform.py
noos_inv/types.py
noos_inv/validators.py
noos_inv-0.2.10.dist-info/LICENSE
noos_inv-0.2.10.dist-info/METADATA
noos_inv-0.2.10.dist-info/WHEEL
noos_inv-0.2.10.dist-info/entry_points.txt
noos_inv-0.2.10.dist-info/RECORD
