Metadata-Version: 2.1
Name: noos-inv
Version: 0.2.10
Summary: Shared workflows across CI/CD pipelines
Home-page: https://github.com/noosenergy/noos-invoke
License: MIT
Author: Noos Energy
Author-email: contact@noos.energy
Requires-Python: >=3.12,<4.0
Classifier: Development Status :: 5 - Production/Stable
Classifier: Environment :: Console
Classifier: Intended Audience :: Developers
Classifier: License :: OSI Approved :: MIT License
Classifier: Operating System :: MacOS
Classifier: Operating System :: POSIX :: Linux
Classifier: Programming Language :: Python :: 3
Classifier: Programming Language :: Python :: 3.12
Classifier: Programming Language :: Python :: 3.13
Classifier: Topic :: Software Development :: Build Tools
Classifier: Typing :: Typed
Requires-Dist: invoke
